{
  "object" : "block",
  "id" : "27af521e-2b70-8053-a5b8-e5b5c244748b",
  "parent" : {
    "type" : "block_id",
    "block_id" : "27af521e-2b70-8032-a184-c1207ec944b3"
  },
  "created_time" : "2025-09-26T20:14:00.000Z",
  "last_edited_time" : "2025-09-26T20:14:00.000Z",
  "created_by" : {
    "object" : "user",
    "id" : "277d872b-594c-815d-ac0f-00023df22fd2"
  },
  "last_edited_by" : {
    "object" : "user",
    "id" : "277d872b-594c-815d-ac0f-00023df22fd2"
  },
  "has_children" : false,
  "archived" : false,
  "in_trash" : false,
  "type" : "paragraph",
  "paragraph" : {
    "rich_text" : [ {
      "type" : "text",
      "text" : {
        "content" : "E1. Invalid Format",
        "link" : null
      },
      "annotations" : {
        "bold" : true,
        "italic" : false,
        "strikethrough" : false,
        "underline" : false,
        "code" : false,
        "color" : "default"
      },
      "plain_text" : "E1. Invalid Format",
      "href" : null
    }, {
      "type" : "text",
      "text" : {
        "content" : " → Reject with message: ",
        "link" : null
      },
      "annotations" : {
        "bold" : false,
        "italic" : false,
        "strikethrough" : false,
        "underline" : false,
        "code" : false,
        "color" : "default"
      },
      "plain_text" : " → Reject with message: ",
      "href" : null
    }, {
      "type" : "text",
      "text" : {
        "content" : "“Invalid card number.”",
        "link" : null
      },
      "annotations" : {
        "bold" : false,
        "italic" : true,
        "strikethrough" : false,
        "underline" : false,
        "code" : false,
        "color" : "default"
      },
      "plain_text" : "“Invalid card number.”",
      "href" : null
    } ],
    "color" : "default"
  }
}