[ {
  "object" : "block",
  "id" : "27cf521e-2b70-8025-afda-c74aae317d33",
  "parent" : {
    "type" : "page_id",
    "page_id" : "27cf521e-2b70-80ca-93e3-d420ede3f38b"
  },
  "created_time" : "2025-09-28T02:23:00.000Z",
  "last_edited_time" : "2025-09-28T02:23:00.000Z",
  "created_by" : {
    "object" : "user",
    "id" : "277d872b-594c-815d-ac0f-00023df22fd2"
  },
  "last_edited_by" : {
    "object" : "user",
    "id" : "277d872b-594c-815d-ac0f-00023df22fd2"
  },
  "has_children" : true,
  "archived" : false,
  "in_trash" : false,
  "type" : "toggle",
  "toggle" : {
    "rich_text" : [ {
      "type" : "text",
      "text" : {
        "content" : "General",
        "link" : null
      },
      "annotations" : {
        "bold" : true,
        "italic" : false,
        "strikethrough" : false,
        "underline" : false,
        "code" : false,
        "color" : "default"
      },
      "plain_text" : "General",
      "href" : null
    } ],
    "color" : "default"
  },
  "children" : [ {
    "object" : "block",
    "id" : "27cf521e-2b70-8046-b7a2-cde35fe05495",
    "parent" : {
      "type" : "block_id",
      "block_id" : "27cf521e-2b70-8025-afda-c74aae317d33"
    },
    "created_time" : "2025-09-28T02:23:00.000Z",
    "last_edited_time" : "2025-09-28T02:25:00.000Z",
    "created_by" : {
      "object" : "user",
      "id" : "277d872b-594c-815d-ac0f-00023df22fd2"
    },
    "last_edited_by" : {
      "object" : "user",
      "id" : "277d872b-594c-815d-ac0f-00023df22fd2"
    },
    "has_children" : false,
    "archived" : false,
    "in_trash" : false,
    "type" : "paragraph",
    "paragraph" : {
      "rich_text" : [ {
        "type" : "text",
        "text" : {
          "content" : "The ",
          "link" : null
        },
        "annotations" : {
          "bold" : false,
          "italic" : false,
          "strikethrough" : false,
          "underline" : false,
          "code" : false,
          "color" : "default"
        },
        "plain_text" : "The ",
        "href" : null
      }, {
        "type" : "text",
        "text" : {
          "content" : "Issuer System / Bank",
          "link" : null
        },
        "annotations" : {
          "bold" : true,
          "italic" : false,
          "strikethrough" : false,
          "underline" : false,
          "code" : false,
          "color" : "default"
        },
        "plain_text" : "Issuer System / Bank",
        "href" : null
      }, {
        "type" : "text",
        "text" : {
          "content" : " is the financial institution that provides payment instruments (such as credit cards, debit cards, or virtual accounts) to customers, manages their accounts, and guarantees payment to merchants on behalf of the customer. The issuer is responsible for maintaining the customer’s balance or credit line, ensuring security of payment credentials, and offering related services such as statements, rewards, and dispute handling.",
          "link" : null
        },
        "annotations" : {
          "bold" : false,
          "italic" : false,
          "strikethrough" : false,
          "underline" : false,
          "code" : false,
          "color" : "default"
        },
        "plain_text" : " is the financial institution that provides payment instruments (such as credit cards, debit cards, or virtual accounts) to customers, manages their accounts, and guarantees payment to merchants on behalf of the customer. The issuer is responsible for maintaining the customer’s balance or credit line, ensuring security of payment credentials, and offering related services such as statements, rewards, and dispute handling.",
        "href" : null
      } ],
      "color" : "default"
    }
  } ]
}, {
  "object" : "block",
  "id" : "27cf521e-2b70-8017-b897-cecb295fe222",
  "parent" : {
    "type" : "page_id",
    "page_id" : "27cf521e-2b70-80ca-93e3-d420ede3f38b"
  },
  "created_time" : "2025-09-28T02:23:00.000Z",
  "last_edited_time" : "2025-09-28T02:23:00.000Z",
  "created_by" : {
    "object" : "user",
    "id" : "277d872b-594c-815d-ac0f-00023df22fd2"
  },
  "last_edited_by" : {
    "object" : "user",
    "id" : "277d872b-594c-815d-ac0f-00023df22fd2"
  },
  "has_children" : true,
  "archived" : false,
  "in_trash" : false,
  "type" : "toggle",
  "toggle" : {
    "rich_text" : [ {
      "type" : "text",
      "text" : {
        "content" : "Focused",
        "link" : null
      },
      "annotations" : {
        "bold" : true,
        "italic" : false,
        "strikethrough" : false,
        "underline" : false,
        "code" : false,
        "color" : "default"
      },
      "plain_text" : "Focused",
      "href" : null
    } ],
    "color" : "default"
  },
  "children" : [ {
    "object" : "block",
    "id" : "27cf521e-2b70-8012-9ac2-d3ef68cec728",
    "parent" : {
      "type" : "block_id",
      "block_id" : "27cf521e-2b70-8017-b897-cecb295fe222"
    },
    "created_time" : "2025-09-28T02:23:00.000Z",
    "last_edited_time" : "2025-09-28T03:10:00.000Z",
    "created_by" : {
      "object" : "user",
      "id" : "277d872b-594c-815d-ac0f-00023df22fd2"
    },
    "last_edited_by" : {
      "object" : "user",
      "id" : "277d872b-594c-815d-ac0f-00023df22fd2"
    },
    "has_children" : false,
    "archived" : false,
    "in_trash" : false,
    "type" : "paragraph",
    "paragraph" : {
      "rich_text" : [ {
        "type" : "text",
        "text" : {
          "content" : "In the ",
          "link" : null
        },
        "annotations" : {
          "bold" : false,
          "italic" : false,
          "strikethrough" : false,
          "underline" : false,
          "code" : false,
          "color" : "default"
        },
        "plain_text" : "In the ",
        "href" : null
      }, {
        "type" : "text",
        "text" : {
          "content" : "Payment Pipeline",
          "link" : null
        },
        "annotations" : {
          "bold" : true,
          "italic" : false,
          "strikethrough" : false,
          "underline" : false,
          "code" : false,
          "color" : "default"
        },
        "plain_text" : "Payment Pipeline",
        "href" : null
      }, {
        "type" : "text",
        "text" : {
          "content" : ", the ",
          "link" : null
        },
        "annotations" : {
          "bold" : false,
          "italic" : false,
          "strikethrough" : false,
          "underline" : false,
          "code" : false,
          "color" : "default"
        },
        "plain_text" : ", the ",
        "href" : null
      }, {
        "type" : "text",
        "text" : {
          "content" : "Issuer",
          "link" : null
        },
        "annotations" : {
          "bold" : true,
          "italic" : false,
          "strikethrough" : false,
          "underline" : false,
          "code" : false,
          "color" : "default"
        },
        "plain_text" : "Issuer",
        "href" : null
      }, {
        "type" : "text",
        "text" : {
          "content" : " acts as the authorizing party that validates the customer’s payment credentials, checks available funds or credit, applies fraud and risk controls, and returns an approval or decline response to the ",
          "link" : null
        },
        "annotations" : {
          "bold" : false,
          "italic" : false,
          "strikethrough" : false,
          "underline" : false,
          "code" : false,
          "color" : "default"
        },
        "plain_text" : " acts as the authorizing party that validates the customer’s payment credentials, checks available funds or credit, applies fraud and risk controls, and returns an approval or decline response to the ",
        "href" : null
      }, {
        "type" : "text",
        "text" : {
          "content" : "Network",
          "link" : null
        },
        "annotations" : {
          "bold" : true,
          "italic" : false,
          "strikethrough" : false,
          "underline" : false,
          "code" : false,
          "color" : "default"
        },
        "plain_text" : "Network",
        "href" : null
      }, {
        "type" : "text",
        "text" : {
          "content" : ".",
          "link" : null
        },
        "annotations" : {
          "bold" : false,
          "italic" : false,
          "strikethrough" : false,
          "underline" : false,
          "code" : false,
          "color" : "default"
        },
        "plain_text" : ".",
        "href" : null
      } ],
      "color" : "default"
    }
  } ]
} ]