{
  "object" : "block",
  "id" : "27af521e-2b70-80c7-87ba-d77c1066b168",
  "parent" : {
    "type" : "block_id",
    "block_id" : "27af521e-2b70-8072-bba9-cf0a4baa6c73"
  },
  "created_time" : "2025-09-26T19:32:00.000Z",
  "last_edited_time" : "2025-09-26T19:32:00.000Z",
  "created_by" : {
    "object" : "user",
    "id" : "277d872b-594c-815d-ac0f-00023df22fd2"
  },
  "last_edited_by" : {
    "object" : "user",
    "id" : "277d872b-594c-815d-ac0f-00023df22fd2"
  },
  "has_children" : false,
  "archived" : false,
  "in_trash" : false,
  "type" : "bulleted_list_item",
  "bulleted_list_item" : {
    "rich_text" : [ {
      "type" : "text",
      "text" : {
        "content" : "System sends a cancellation request to the provider (Napas gateway, wallet API, bank API).",
        "link" : null
      },
      "annotations" : {
        "bold" : false,
        "italic" : false,
        "strikethrough" : false,
        "underline" : false,
        "code" : false,
        "color" : "default"
      },
      "plain_text" : "System sends a cancellation request to the provider (Napas gateway, wallet API, bank API).",
      "href" : null
    } ],
    "color" : "default"
  }
}