{
  "object" : "page",
  "id" : "27cf521e-2b70-80bf-b4ce-f8e42de7e4eb",
  "created_time" : "2025-09-28T10:37:00.000Z",
  "last_edited_time" : "2025-09-28T10:39:00.000Z",
  "created_by" : {
    "object" : "user",
    "id" : "277d872b-594c-815d-ac0f-00023df22fd2"
  },
  "last_edited_by" : {
    "object" : "user",
    "id" : "277d872b-594c-815d-ac0f-00023df22fd2"
  },
  "cover" : null,
  "icon" : {
    "type" : "emoji",
    "emoji" : "🛡️"
  },
  "parent" : {
    "type" : "database_id",
    "database_id" : "278f521e-2b70-8020-bf7a-c18805532ce2"
  },
  "archived" : false,
  "in_trash" : false,
  "is_locked" : false,
  "properties" : {
    "Actor" : {
      "id" : "Yz%40%60",
      "type" : "select",
      "select" : {
        "id" : "81887d16-f453-46d7-bfd3-661a90b248bc",
        "name" : "F&R",
        "color" : "orange"
      }
    },
    "Business" : {
      "id" : "b%7Bxb",
      "type" : "select",
      "select" : {
        "id" : "fca8c6f7-e3b6-4df2-8dc0-21a80b28fcc7",
        "name" : "Authorize",
        "color" : "orange"
      }
    },
    "Status" : {
      "id" : "k%3FMm",
      "type" : "status",
      "status" : {
        "id" : "8e60037a-bd86-4bec-ae03-6dcd5c392137",
        "name" : "Not started",
        "color" : "default"
      }
    },
    "Priority" : {
      "id" : "lgXk",
      "type" : "select",
      "select" : {
        "id" : "q_d^",
        "name" : "P2",
        "color" : "pink"
      }
    },
    "Title" : {
      "id" : "title",
      "type" : "title",
      "title" : [ {
        "type" : "text",
        "text" : {
          "content" : "⏸️📦 F&R Auth",
          "link" : null
        },
        "annotations" : {
          "bold" : false,
          "italic" : false,
          "strikethrough" : false,
          "underline" : false,
          "code" : false,
          "color" : "default"
        },
        "plain_text" : "⏸️📦 F&R Auth",
        "href" : null
      } ]
    }
  },
  "url" : "https://www.notion.so/F-R-Auth-27cf521e2b7080bfb4cef8e42de7e4eb",
  "public_url" : null
}